setup.py
mxplient/__init__.py
mxplient/mxobject.py
mxplient/mxplient.py
mxplient/version.py
mxplient.egg-info/PKG-INFO
mxplient.egg-info/SOURCES.txt
mxplient.egg-info/dependency_links.txt
mxplient.egg-info/not-zip-safe
mxplient.egg-info/top_level.txt