Metadata-Version: 1.0
Name: mxplient
Version: 0.1
Summary: A mendix protocol client
Home-page: http://github.com/storborg/funniest
Author: Mendix
Author-email: hans.then@mendix.com
License: MIT
Platform: UNKNOWN
